mockend/__init__.py
mockend/__main__.py
mockend/_version.py
mockend-0.4.1.dist-info/LICENSE
mockend-0.4.1.dist-info/METADATA
mockend-0.4.1.dist-info/WHEEL
mockend-0.4.1.dist-info/entry_points.txt
mockend-0.4.1.dist-info/top_level.txt
mockend-0.4.1.dist-info/RECORD
