Metadata-Version: 2.1
Name: mockend
Version: 0.4.1
Summary: Mockend is a simple tool for mocking endpoints
Home-page: https://github.com/mghorbani2357/mockend
Author: Mohsen Ghorbani
Author-email: m.ghorbani2357@gmail.com
License: MIT
Platform: UNKNOWN
Classifier: Intended Audience :: Developers
Classifier: License :: OSI Approved :: MIT License
Classifier: Operating System :: MacOS
Classifier: Operating System :: POSIX :: Linux
Classifier: Operating System :: OS Independent
Classifier: Topic :: Software Development :: Libraries :: Python Modules
Classifier: Programming Language :: Python :: Implementation :: PyPy
Requires-Dist: flask
